unicorn_tracer/__init__.py
unicorn_tracer/terminal.py
unicorn_tracer/unicorn_tracer.py
unicorn_tracer/tests/__init__.py
unicorn_tracer/tests/ch20.bin
unicorn_tracer-1.1.1.dist-info/LICENSE
unicorn_tracer-1.1.1.dist-info/METADATA
unicorn_tracer-1.1.1.dist-info/WHEEL
unicorn_tracer-1.1.1.dist-info/top_level.txt
unicorn_tracer-1.1.1.dist-info/RECORD
