Metadata-Version: 2.1
Name: unicorn-tracer
Version: 1.1.1
Summary: memory modifications tracing tool for the unicorn cpu emulator
Home-page: https://github.com/SwitchMan92/unicorn_tracer
Author: Tom Langfeldt
Author-email: UNKNOWN
License: UNKNOWN
Platform: UNKNOWN
Classifier: Programming Language :: Python :: 2.7
Classifier: License :: OSI Approved :: GNU General Public License (GPL)
Classifier: Operating System :: OS Independent
Requires-Python: ==2.*
Requires-Dist: termcolor
Requires-Dist: unicorn
